{
  "captured_at": "2026-05-12T04:00:44.335015+00:00",
  "endpoints": {
    "gamma_markets": {
      "status": 200,
      "schema_ok": true,
      "latency_ms_avg": 65.2,
      "latency_ms_max": 74.7,
      "error": null,
      "healthy": true
    },
    "gamma_events": {
      "status": 200,
      "schema_ok": true,
      "latency_ms_avg": 63.6,
      "latency_ms_max": 89.1,
      "error": null,
      "healthy": true
    },
    "gamma_tags": {
      "status": 200,
      "schema_ok": true,
      "latency_ms_avg": 61.2,
      "latency_ms_max": 89.6,
      "error": null,
      "healthy": true
    },
    "clob_markets": {
      "status": 200,
      "schema_ok": true,
      "latency_ms_avg": 130.6,
      "latency_ms_max": 158.5,
      "error": null,
      "healthy": true
    },
    "clob_book": {
      "status": 200,
      "schema_ok": true,
      "latency_ms_avg": 80.4,
      "latency_ms_max": 83.7,
      "error": null,
      "healthy": true
    },
    "kalshi_markets": {
      "status": 200,
      "schema_ok": true,
      "latency_ms_avg": 83.8,
      "latency_ms_max": 160.0,
      "error": null,
      "healthy": true
    },
    "polygon_rpc": {
      "status": 200,
      "schema_ok": true,
      "latency_ms_avg": 91.8,
      "latency_ms_max": 107.1,
      "error": null,
      "healthy": true
    }
  }
}