{
  "last_scan": "2026-04-23T03:23:04.853264+00:00",
  "scan_seconds": 14.2,
  "markets_scanned": 53,
  "open_positions": 13,
  "signals": [
    {
      "id": "sig_1776914573806_0",
      "timestamp": "2026-04-23T03:22:53.806511+00:00",
      "source": "PERPLEXITY",
      "headline": "Ethereum April 11 $2,400 Prediction Market Settles at 100% YES After 22 New Developments Announced** | **YES** | **HIGH*",
      "raw": "Ethereum April 11 $2,400 Prediction Market Settles at 100% YES After 22 New Developments Announced** | **YES** | **HIGH** confidence[1][8]\n\nPrediction market on Polymarket for Ethereum reaching $2,400 by April 11 resolved to 100% YES, up from 18% prior, following Ethereum Foundation's announcement of 22 developments on scalability, privacy, and interoperability aligning with 2026 priorities[1]. Tr",
      "direction": "YES",
      "confidence": 0.9,
      "matched_markets": [
        "Bitcoin above 79,000 on April 23, 12AM ET?",
        "Will Bitcoin reach $82,500 in April?",
        "Ethereum Up or Down - April 23, 2:30AM-2:35AM ET"
      ],
      "action": "ENTER",
      "x_link": null,
      "category": "CRYPTO"
    },
    {
      "id": "sig_1776914578906_1",
      "timestamp": "2026-04-23T03:22:58.906843+00:00",
      "source": "PERPLEXITY",
      "headline": "Spurs' Keldon Johnson wins 2025-26 NBA Sixth Man of the Year | YES | HIGH confidence**",
      "raw": "Spurs' Keldon Johnson wins 2025-26 NBA Sixth Man of the Year | YES | HIGH confidence**  \nJohnson was awarded the honor, a newly resolved postseason accolade for the Spurs bench standout.[4]  \nThis announcement may influence minor markets on individual awards or Spurs playoff props, though less market-moving than injuries.[4]  \n\nNo confirmed breaking news on **Raptors** (No. 5 East seed, play-in se",
      "direction": "YES",
      "confidence": 0.65,
      "matched_markets": [
        "Will Cooper Flagg win the 2025\u201326 NBA Rookie of the Year award?",
        "NBA Playoffs: Who Will Win Series? - Raptors vs. Cavaliers ",
        "Will Los Angeles Lakers advance to the Conference Semifinals in the 2026 NBA Pla"
      ],
      "action": "ALERT",
      "x_link": null,
      "category": "SPORTS"
    },
    {
      "id": "sig_1776914583845_0",
      "timestamp": "2026-04-23T03:23:03.845757+00:00",
      "source": "PERPLEXITY",
      "headline": "No major whale bets, smart money moves, or prediction market tips from Polymarket traders on X are breaking right now",
      "raw": "No major whale bets, smart money moves, or prediction market tips from Polymarket traders on X are breaking right now.** Search results highlight trending Polymarket categories like **Trending Markets** (e.g., Kinetiq price in 2026, Nasdaq 24/7 trading by June 30 at implied odds, law banning sports prediction markets in 2026) with $3M+ volume, **Tweet Markets** (e.g., Elon Musk tweet counts in Apr",
      "direction": "YES",
      "confidence": 0.65,
      "matched_markets": [
        "Will Trump name \"Elon\" or \"Musk\" in April?"
      ],
      "action": "ALERT",
      "x_link": null,
      "category": "COMMUNITY"
    },
    {
      "id": "sig_1776914583849_1",
      "timestamp": "2026-04-23T03:23:03.849511+00:00",
      "source": "PERPLEXITY",
      "headline": "Confidence: LOW**\u2014results snapshot Polymarket pages as of April 21-22, 2026, lacking live X trader chatter, whale alerts",
      "raw": "Confidence: LOW**\u2014results snapshot Polymarket pages as of April 21-22, 2026, lacking live X trader chatter, whale alerts, or breaking confirmations at 3 AM UTC[6].",
      "direction": null,
      "confidence": 0.65,
      "matched_markets": [],
      "action": "ALERT",
      "x_link": null,
      "category": "COMMUNITY"
    },
    {
      "id": "sig_1776914578904_0",
      "timestamp": "2026-04-23T03:22:58.904668+00:00",
      "source": "PERPLEXITY",
      "headline": "Spurs' Victor Wembanyama ruled out with concussion after Game 2 fall vs",
      "raw": "Spurs' Victor Wembanyama ruled out with concussion after Game 2 fall vs. Trail Blazers | YES | HIGH confidence**  \nWembanyama exited San Antonio's Game 2 playoff loss and was quickly ruled out, impacting the No. 2 seed Spurs' series against No. 7 Portland amid ongoing first-round matchups.[2][4]  \nThis recent injury confirmation could shift prediction markets on Spurs advancement, MVP futures, and",
      "direction": "YES",
      "confidence": 0.6,
      "matched_markets": [],
      "action": "WATCH",
      "x_link": null,
      "category": "SPORTS"
    }
  ],
  "stats": {
    "enter": 1,
    "alert": 3,
    "watch": 1,
    "high_conf": 1
  }
}