{
  "last_scan": "2026-04-16T00:34:13.862722+00:00",
  "scan_seconds": 35.5,
  "markets_scanned": 78,
  "open_positions": 40,
  "signals": [
    {
      "id": "sig_414692",
      "timestamp": "2026-04-16T00:33:58.391172+00:00",
      "source": "PERPLEXITY",
      "headline": "IRAN CEASEFIRE AND PEACE TALKS ONGOING | PARTIALLY CONFIRMED | MED confidence**",
      "raw": "IRAN CEASEFIRE AND PEACE TALKS ONGOING | PARTIALLY CONFIRMED | MED confidence**\n\nWhite House Press Secretary Karoline Leavitt confirmed that peace talks with Iran are ongoing and progressing, though no final agreement has been reached[3]. The White House pushed back on reports of a confirmed ceasefire, emphasizing negotiations are still evolving[3]. Trump has announced a two-week ceasefire framewo",
      "direction": "NO",
      "confidence": 0.9,
      "matched_markets": [
        "Will the US x Iran ceasefire be extended by April 21, 2026?",
        "Trump announces end of military operations against Iran by A"
      ],
      "action": "ENTER",
      "x_link": null,
      "category": "POLITICS"
    },
    {
      "id": "sig_423817",
      "timestamp": "2026-04-16T00:34:07.516644+00:00",
      "source": "PERPLEXITY",
      "headline": "I cannot provide breaking news in the format you've requested based on these search results",
      "raw": "I cannot provide breaking news in the format you've requested based on these search results. The most recent information available is from April 14, 2026, when **Bitcoin broke through $74,000 resistance to reach a one-month high near $75,000**[3], driven by strong ETF inflows and institutional demand.\n\nHowever, the search results do not contain any confirmed announcements, resolutions, or market-m",
      "direction": "YES",
      "confidence": 0.9,
      "matched_markets": [
        "Will the US x Iran ceasefire be extended by April 21, 2026?",
        "US x Iran diplomatic meeting by April 18, 2026?",
        "US x Iran permanent peace deal by April 30, 2026?"
      ],
      "action": "ENTER",
      "x_link": null,
      "category": "CRYPTO"
    },
    {
      "id": "sig_414674",
      "timestamp": "2026-04-16T00:33:58.373239+00:00",
      "source": "PERPLEXITY",
      "headline": "Based on the search results provided, here are the key confirmed developments:",
      "raw": "Based on the search results provided, here are the key confirmed developments:",
      "direction": null,
      "confidence": 0.9,
      "matched_markets": [],
      "action": "ALERT",
      "x_link": null,
      "category": "POLITICS"
    },
    {
      "id": "sig_414680",
      "timestamp": "2026-04-16T00:33:58.379197+00:00",
      "source": "PERPLEXITY",
      "headline": "VANCE FORMALLY NAMED \"FRAUD CZAR\" BY TRUMP | YES | HIGH confidence**",
      "raw": "VANCE FORMALLY NAMED \"FRAUD CZAR\" BY TRUMP | YES | HIGH confidence**\n\nVice President JD Vance has been officially designated as **\"fraud czar\"** following his task force's busting of an alleged $50 million hospice and healthcare fraud scheme in Los Angeles[1]. Trump announced this on Truth Social, emphasizing that Vance's focus will be \"EVERYWHERE\" but with special emphasis on Democratic-controlle",
      "direction": "YES",
      "confidence": 0.9,
      "matched_markets": [],
      "action": "ALERT",
      "x_link": null,
      "category": "POLITICS"
    },
    {
      "id": "sig_429163",
      "timestamp": "2026-04-16T00:34:12.862081+00:00",
      "source": "PERPLEXITY",
      "headline": "Trump Nominates Kevin Warsh as Fed Chair, Sparking Uncertainty on Inflation Policy and Dollar Strength; South Korean Won",
      "raw": "Trump Nominates Kevin Warsh as Fed Chair, Sparking Uncertainty on Inflation Policy and Dollar Strength; South Korean Won Weakens Amid Trade Tensions** | YES | HIGH confidence\n\nPresident Trump's nomination of Kevin Warsh to lead the Fed has been reported as a key development adding uncertainty, with traders focusing on his **hawkish approach to inflation** and potential for a stronger dollar, contr",
      "direction": "YES",
      "confidence": 0.78,
      "matched_markets": [
        "Kevin Warsh confirmed as Fed Chair by May 15?",
        "Will South Korea\u2019s 2026 Annual Inflation be between 2.7% and 2.9%?"
      ],
      "action": "ALERT",
      "x_link": null,
      "category": "ECONOMICS"
    },
    {
      "id": "sig_414686",
      "timestamp": "2026-04-16T00:33:58.385262+00:00",
      "source": "PERPLEXITY",
      "headline": "CABINET SHUFFLING: BONDI AND NOEM REMOVED | YES | HIGH confidence**",
      "raw": "CABINET SHUFFLING: BONDI AND NOEM REMOVED | YES | HIGH confidence**\n\nTrump has removed Attorney General Pam Bondi from the Department of Justice and previously removed Homeland Security Secretary Kristi Noem[1]. Political analyst Jonathan Turley characterized Bondi's removal as hitting Washington \"like a thunderclap\"[1].",
      "direction": "YES",
      "confidence": 0.65,
      "matched_markets": [],
      "action": "ALERT",
      "x_link": null,
      "category": "POLITICS"
    }
  ],
  "stats": {
    "enter": 2,
    "alert": 4,
    "watch": 0,
    "high_conf": 4
  }
}