{
  "last_scan": "2026-04-22T22:33:05.601577+00:00",
  "scan_seconds": 15.0,
  "markets_scanned": 47,
  "open_positions": 13,
  "signals": [
    {
      "id": "sig_1776897175705_0",
      "timestamp": "2026-04-22T22:32:55.705682+00:00",
      "source": "PERPLEXITY",
      "headline": "Based on the search results provided, I cannot identify any breaking news from today (April 22, 2026) that would move pr",
      "raw": "Based on the search results provided, I cannot identify any breaking news from today (April 22, 2026) that would move prediction markets. The most recent dated source is from April 20, 2026, which shows Ethereum trading at $2,317.80[3], representing a modest $25.16 decrease from the previous day.\n\nThe search results contain several significant developments from earlier in April that *previously* m",
      "direction": "NO",
      "confidence": 0.65,
      "matched_markets": [
        "Ethereum Up or Down - April 23, 2:30AM-2:35AM ET"
      ],
      "action": "ALERT",
      "x_link": null,
      "category": "CRYPTO"
    },
    {
      "id": "sig_1776897175707_1",
      "timestamp": "2026-04-22T22:32:55.707560+00:00",
      "source": "PERPLEXITY",
      "headline": "**Ethereum Foundation Staking 70,000 ETH ($143M) | YES | HIGH** \u2014 The Foundation shifted strategy to stake rather than s",
      "raw": "**Ethereum Foundation Staking 70,000 ETH ($143M) | YES | HIGH** \u2014 The Foundation shifted strategy to stake rather than sell, reducing supply pressure[1][4]",
      "direction": "YES",
      "confidence": 0.65,
      "matched_markets": [],
      "action": "ALERT",
      "x_link": null,
      "category": "CRYPTO"
    },
    {
      "id": "sig_1776897175709_2",
      "timestamp": "2026-04-22T22:32:55.709378+00:00",
      "source": "PERPLEXITY",
      "headline": "**Spot Ethereum ETF Inflows Surge ($187M net inflows, BlackRock $168M) | YES | HIGH** \u2014 Institutional demand spike recor",
      "raw": "**Spot Ethereum ETF Inflows Surge ($187M net inflows, BlackRock $168M) | YES | HIGH** \u2014 Institutional demand spike recorded last week of April[4]",
      "direction": "YES",
      "confidence": 0.65,
      "matched_markets": [
        "Ethereum Up or Down - April 23, 2:30AM-2:35AM ET"
      ],
      "action": "ALERT",
      "x_link": null,
      "category": "CRYPTO"
    },
    {
      "id": "sig_1776897175711_3",
      "timestamp": "2026-04-22T22:32:55.711202+00:00",
      "source": "PERPLEXITY",
      "headline": "**Pectra (Prague-Electra) Upgrade Enters Final Testing | YES | MED** \u2014 Network upgrade promises wallet abstraction impro",
      "raw": "**Pectra (Prague-Electra) Upgrade Enters Final Testing | YES | MED** \u2014 Network upgrade promises wallet abstraction improvements as of mid-April[5]\n\nHowever, none of these represent *breaking news from today*. To provide accurate breaking news confirmation from April 22, 2026 at 10 PM UTC, I would need search results dated from today.",
      "direction": "YES",
      "confidence": 0.65,
      "matched_markets": [],
      "action": "ALERT",
      "x_link": null,
      "category": "CRYPTO"
    },
    {
      "id": "sig_1776897180111_0",
      "timestamp": "2026-04-22T22:33:00.111019+00:00",
      "source": "PERPLEXITY",
      "headline": "Lakers Take 2-0 Lead Over Rockets in First Round | YES (Lakers Surge in Odds, Impacting Prediction Markets) | HIGH confi",
      "raw": "Lakers Take 2-0 Lead Over Rockets in First Round | YES (Lakers Surge in Odds, Impacting Prediction Markets) | HIGH confidence** [1]\n\nThe Los Angeles Lakers, despite injuries to Luka Doncic (hamstring) and Austin Reaves (oblique), have won the first two games of their first-round playoff series against the Houston Rockets, flipping their NBA Finals odds from 150-1 longshots to 35-1 favorites and ma",
      "direction": "YES",
      "confidence": 0.65,
      "matched_markets": [
        "Will Cooper Flagg win the 2025\u201326 NBA Rookie of the Year award?",
        "NBA Playoffs: Who Will Win Series? - Raptors vs. Cavaliers ",
        "Will Los Angeles Lakers advance to the Conference Semifinals in the 2026 NBA Pla"
      ],
      "action": "ALERT",
      "x_link": null,
      "category": "SPORTS"
    },
    {
      "id": "sig_1776897184598_0",
      "timestamp": "2026-04-22T22:33:04.598138+00:00",
      "source": "PERPLEXITY",
      "headline": "Elon Musk April 2026 Tweet Count Markets Trending on Polymarket | NO | HIGH confidence**",
      "raw": "Elon Musk April 2026 Tweet Count Markets Trending on Polymarket | NO | HIGH confidence**\n\nPolymarket's most active markets right now focus on **Elon Musk's tweet volume in April 2026**, with the \"Elon Musk # tweets in April 2026?\" market showing the outcome \"1120-1159\" priced at 20-21% implied probability and over $20.7M in trading volume[3][4]. These tweet prediction markets (130+ live as of earl",
      "direction": "NO",
      "confidence": 0.65,
      "matched_markets": [
        "Will Trump name \"Elon\" or \"Musk\" in April?"
      ],
      "action": "ALERT",
      "x_link": null,
      "category": "COMMUNITY"
    }
  ],
  "stats": {
    "enter": 0,
    "alert": 6,
    "watch": 0,
    "high_conf": 0
  }
}