{
  "last_scan": "2026-04-22T14:43:37.802958+00:00",
  "scan_seconds": 17.2,
  "markets_scanned": 74,
  "open_positions": 38,
  "signals": [
    {
      "id": "sig_1776869016791_4",
      "timestamp": "2026-04-22T14:43:36.791439+00:00",
      "source": "PERPLEXITY",
      "headline": "Recent announcements or market-moving news that has just been confirmed",
      "raw": "Recent announcements or market-moving news that has just been confirmed\n\nTo get this information, you would need to:",
      "direction": null,
      "confidence": 0.9,
      "matched_markets": [],
      "action": "ALERT",
      "x_link": null,
      "category": "COMMUNITY"
    },
    {
      "id": "sig_1776869009768_0",
      "timestamp": "2026-04-22T14:43:29.768090+00:00",
      "source": "PERPLEXITY",
      "headline": "LOW confidence** in any market-moving event due to lack of real-time confirmations post-Game 1/2 window",
      "raw": "LOW confidence** in any market-moving event due to lack of real-time confirmations post-Game 1/2 window.[2]",
      "direction": null,
      "confidence": 0.65,
      "matched_markets": [],
      "action": "ALERT",
      "x_link": null,
      "category": "SPORTS"
    },
    {
      "id": "sig_1776869016780_0",
      "timestamp": "2026-04-22T14:43:36.780163+00:00",
      "source": "PERPLEXITY",
      "headline": "I cannot provide the specific real-time information you're requesting based on these search results",
      "raw": "I cannot provide the specific real-time information you're requesting based on these search results. The search results provided describe Polymarket's general functionality and historical market examples (such as Elon Musk tweet count predictions from mid-April 2026), but they do not contain:",
      "direction": null,
      "confidence": 0.65,
      "matched_markets": [],
      "action": "ALERT",
      "x_link": null,
      "category": "COMMUNITY"
    },
    {
      "id": "sig_1776869016782_1",
      "timestamp": "2026-04-22T14:43:36.782930+00:00",
      "source": "PERPLEXITY",
      "headline": "Current X (Twitter) posts from Polymarket traders",
      "raw": "Current X (Twitter) posts from Polymarket traders",
      "direction": null,
      "confidence": 0.65,
      "matched_markets": [],
      "action": "ALERT",
      "x_link": null,
      "category": "COMMUNITY"
    },
    {
      "id": "sig_1776869016785_2",
      "timestamp": "2026-04-22T14:43:36.785629+00:00",
      "source": "PERPLEXITY",
      "headline": "Active whale bets or smart money moves happening right now",
      "raw": "Active whale bets or smart money moves happening right now",
      "direction": null,
      "confidence": 0.65,
      "matched_markets": [],
      "action": "ALERT",
      "x_link": null,
      "category": "COMMUNITY"
    },
    {
      "id": "sig_1776869016788_3",
      "timestamp": "2026-04-22T14:43:36.788602+00:00",
      "source": "PERPLEXITY",
      "headline": "Real-time discussions about mispriced markets",
      "raw": "Real-time discussions about mispriced markets",
      "direction": null,
      "confidence": 0.65,
      "matched_markets": [],
      "action": "ALERT",
      "x_link": null,
      "category": "COMMUNITY"
    }
  ],
  "stats": {
    "enter": 0,
    "alert": 6,
    "watch": 0,
    "high_conf": 1
  }
}