{
  "last_scan": "2026-04-22T18:18:26.843517+00:00",
  "scan_seconds": 26.3,
  "markets_scanned": 52,
  "open_positions": 14,
  "signals": [
    {
      "id": "sig_1776881905832_0",
      "timestamp": "2026-04-22T18:18:25.832280+00:00",
      "source": "PERPLEXITY",
      "headline": "Trending Polymarket Discussions on X: Limited Real-Time Intel from Available Data**",
      "raw": "Trending Polymarket Discussions on X: Limited Real-Time Intel from Available Data**\n\nPolymarket traders on X are likely buzzing about **Elon Musk tweet volume markets** and **Bitcoin price thresholds**, as these show high trading volumes and specificity in current listings, though direct X posts aren't captured here.[2][3] No explicit whale bets, smart money moves, or tips are detailed in results,",
      "direction": "NO",
      "confidence": 0.78,
      "matched_markets": [],
      "action": "ALERT",
      "x_link": null,
      "category": "COMMUNITY"
    },
    {
      "id": "sig_1776881892411_0",
      "timestamp": "2026-04-22T18:18:12.411293+00:00",
      "source": "PERPLEXITY",
      "headline": "Based on the search results, here are the key developments that would move prediction markets:",
      "raw": "Based on the search results, here are the key developments that would move prediction markets:",
      "direction": null,
      "confidence": 0.65,
      "matched_markets": [],
      "action": "ALERT",
      "x_link": null,
      "category": "CRYPTO"
    },
    {
      "id": "sig_1776881892413_1",
      "timestamp": "2026-04-22T18:18:12.413401+00:00",
      "source": "PERPLEXITY",
      "headline": "Solana Hits 167M Monthly Token Holders & Alpenglow Upgrade Targets 150ms Finality | YES | HIGH confidence**",
      "raw": "Solana Hits 167M Monthly Token Holders & Alpenglow Upgrade Targets 150ms Finality | YES | HIGH confidence**\n\nAs of April 14, 2026, Solana achieved an all-time record of 167 million monthly token holders with daily non-vote transactions reaching 148 million[1]. The highly anticipated **Alpenglow consensus upgrade** aims to slash transaction finality from 12 seconds to just 150 milliseconds[1]\u2014a tra",
      "direction": "YES",
      "confidence": 0.65,
      "matched_markets": [
        "Will the price of Solana be above $90 on April 28?"
      ],
      "action": "ALERT",
      "x_link": null,
      "category": "CRYPTO"
    },
    {
      "id": "sig_1776881892415_2",
      "timestamp": "2026-04-22T18:18:12.415511+00:00",
      "source": "PERPLEXITY",
      "headline": "SOL Surges 10% Over Five Days to Three-Week High | YES | HIGH confidence**",
      "raw": "SOL Surges 10% Over Five Days to Three-Week High | YES | HIGH confidence**\n\nSOL climbed 10% over five days, reaching a three-week high on Friday (April 18)[2]. This move followed the US-Iran ceasefire extension announcement, which reduced risk-off sentiment across crypto markets[2]. Futures open interest jumped 20% in under a week, rising from $3.5 billion to $4.2 billion[2].",
      "direction": "YES",
      "confidence": 0.65,
      "matched_markets": [],
      "action": "ALERT",
      "x_link": null,
      "category": "CRYPTO"
    },
    {
      "id": "sig_1776881892417_3",
      "timestamp": "2026-04-22T18:18:12.417543+00:00",
      "source": "PERPLEXITY",
      "headline": "Solana Vastly Outpaces Ethereum in Q1 2026 Transaction Volume | YES | HIGH confidence**",
      "raw": "Solana Vastly Outpaces Ethereum in Q1 2026 Transaction Volume | YES | HIGH confidence**\n\nSolana processed 25.3 billion transactions in Q1 2026, significantly outpacing Ethereum's 200 million transactions[3]. Solana's developer base expanded to 4,100 new developers, capturing 23% developer share while Ethereum's declined[3]. Stablecoin volume on Solana showed 12-fold year-on-year growth, with $1 tr",
      "direction": "YES",
      "confidence": 0.65,
      "matched_markets": [],
      "action": "ALERT",
      "x_link": null,
      "category": "CRYPTO"
    },
    {
      "id": "sig_1776881892419_4",
      "timestamp": "2026-04-22T18:18:12.419534+00:00",
      "source": "PERPLEXITY",
      "headline": "Ethereum Technical Setup: Triple-Bottom Formation Near $2,500 | YES | MEDIUM confidence**",
      "raw": "Ethereum Technical Setup: Triple-Bottom Formation Near $2,500 | YES | MEDIUM confidence**\n\nEthereum shows a \"triple-bottom\" formation around $2,500, suggesting potential bullish setup toward $3,000[4]. ETH futures open interest surged 12% to $14.25 billion[4], indicating institutional confidence in a potential rebound.",
      "direction": "YES",
      "confidence": 0.65,
      "matched_markets": [],
      "action": "ALERT",
      "x_link": null,
      "category": "CRYPTO"
    },
    {
      "id": "sig_1776881899337_0",
      "timestamp": "2026-04-22T18:18:19.337784+00:00",
      "source": "PERPLEXITY",
      "headline": "I cannot provide the breaking news you're requesting because the search results provided do not contain current informat",
      "raw": "I cannot provide the breaking news you're requesting because the search results provided do not contain current information about an ongoing or upcoming Raptors-Lakers series in the 2026 conference semifinals, nor do they mention the Cavaliers in relation to this matchup.\n\nThe search results include:",
      "direction": null,
      "confidence": 0.65,
      "matched_markets": [
        "NBA Playoffs: Who Will Win Series? - Raptors vs. Cavaliers ",
        "Will Los Angeles Lakers advance to the Conference Semifinals in the 2026 NBA Pla"
      ],
      "action": "ALERT",
      "x_link": null,
      "category": "SPORTS"
    },
    {
      "id": "sig_1776881899339_1",
      "timestamp": "2026-04-22T18:18:19.339767+00:00",
      "source": "PERPLEXITY",
      "headline": "A historical article about the Raptors clinching a division title against the Lakers (appears to be from the 2014-15 sea",
      "raw": "A historical article about the Raptors clinching a division title against the Lakers (appears to be from the 2014-15 season based on context)",
      "direction": null,
      "confidence": 0.65,
      "matched_markets": [],
      "action": "ALERT",
      "x_link": null,
      "category": "SPORTS"
    },
    {
      "id": "sig_1776881899345_2",
      "timestamp": "2026-04-22T18:18:19.345750+00:00",
      "source": "PERPLEXITY",
      "headline": "A 2022 Lakers-Raptors game result",
      "raw": "A 2022 Lakers-Raptors game result",
      "direction": null,
      "confidence": 0.65,
      "matched_markets": [],
      "action": "ALERT",
      "x_link": null,
      "category": "SPORTS"
    },
    {
      "id": "sig_1776881899347_3",
      "timestamp": "2026-04-22T18:18:19.347863+00:00",
      "source": "PERPLEXITY",
      "headline": "Information about the 2019 NBA playoffs when the Raptors won their championship",
      "raw": "Information about the 2019 NBA playoffs when the Raptors won their championship\n\nTo provide accurate breaking news in the format you've requested (HEADLINE | YES or NO | HIGH/MED/LOW confidence), I would need search results containing:",
      "direction": "YES",
      "confidence": 0.65,
      "matched_markets": [
        "NBA Playoffs: Who Will Win Series? - Raptors vs. Cavaliers ",
        "Will Los Angeles Lakers advance to the Conference Semifinals in the 2026 NBA Pla",
        "Will Orlando Magic advance to the Conference Semifinals in the 2026 NBA Playoffs"
      ],
      "action": "ALERT",
      "x_link": null,
      "category": "SPORTS"
    },
    {
      "id": "sig_1776881899353_4",
      "timestamp": "2026-04-22T18:18:19.353931+00:00",
      "source": "PERPLEXITY",
      "headline": "Current playoff bracket information for the 2026 NBA season",
      "raw": "Current playoff bracket information for the 2026 NBA season",
      "direction": null,
      "confidence": 0.65,
      "matched_markets": [],
      "action": "ALERT",
      "x_link": null,
      "category": "SPORTS"
    },
    {
      "id": "sig_1776881899355_5",
      "timestamp": "2026-04-22T18:18:19.355829+00:00",
      "source": "PERPLEXITY",
      "headline": "Details about which teams are facing each other in the conference semifinals",
      "raw": "Details about which teams are facing each other in the conference semifinals",
      "direction": null,
      "confidence": 0.65,
      "matched_markets": [],
      "action": "ALERT",
      "x_link": null,
      "category": "SPORTS"
    },
    {
      "id": "sig_1776881899361_6",
      "timestamp": "2026-04-22T18:18:19.361326+00:00",
      "source": "PERPLEXITY",
      "headline": "Any recent announcements, trades, injuries, or developments that would affect series predictions",
      "raw": "Any recent announcements, trades, injuries, or developments that would affect series predictions\n\nIf you're looking for information about a specific ongoing playoff series, please provide more recent search results or clarify which series you're asking about.",
      "direction": null,
      "confidence": 0.65,
      "matched_markets": [],
      "action": "ALERT",
      "x_link": null,
      "category": "SPORTS"
    },
    {
      "id": "sig_1776881905834_1",
      "timestamp": "2026-04-22T18:18:25.834256+00:00",
      "source": "PERPLEXITY",
      "headline": "**Elon Musk # Tweets (April 20-22, 2026)**: Buckets like \"40-64\" at 100% implied probability; traders may see overpricin",
      "raw": "**Elon Musk # Tweets (April 20-22, 2026)**: Buckets like \"40-64\" at 100% implied probability; traders may see overpricing amid real-time updates from his activity.[2]",
      "direction": null,
      "confidence": 0.65,
      "matched_markets": [
        "Will Trump name \"Elon\" or \"Musk\" in April?"
      ],
      "action": "ALERT",
      "x_link": null,
      "category": "COMMUNITY"
    },
    {
      "id": "sig_1776881905838_3",
      "timestamp": "2026-04-22T18:18:25.838305+00:00",
      "source": "PERPLEXITY",
      "headline": "**Bitcoin >$114k on Oct 15",
      "raw": "**Bitcoin >$114k on Oct 15?**: Yes at 16.5\u00a2 held by @xtrader (1,300 shares); low odds suggest mispricing bets on crypto rallies.[4]",
      "direction": "YES",
      "confidence": 0.65,
      "matched_markets": [],
      "action": "ALERT",
      "x_link": null,
      "category": "COMMUNITY"
    },
    {
      "id": "sig_1776881905836_2",
      "timestamp": "2026-04-22T18:18:25.836258+00:00",
      "source": "PERPLEXITY",
      "headline": "**Elon Musk # Tweets in April 2026 (1120-1159 bucket)**: 18% odds with $22",
      "raw": "**Elon Musk # Tweets in April 2026 (1120-1159 bucket)**: 18% odds with $22.2M volume\u2014possible smart money fade if tweet pace accelerates.[3]",
      "direction": null,
      "confidence": 0.6,
      "matched_markets": [
        "Will Trump name \"Elon\" or \"Musk\" in April?"
      ],
      "action": "WATCH",
      "x_link": null,
      "category": "COMMUNITY"
    },
    {
      "id": "sig_1776881905840_4",
      "timestamp": "2026-04-22T18:18:25.840612+00:00",
      "source": "PERPLEXITY",
      "headline": "Broader **Trending Markets** (168 active, e",
      "raw": "Broader **Trending Markets** (168 active, e.g., \"Nasdaq 24/7 by June 30?\"): Real-time odds from $2.8M volume could shift on tech news.[1]\n\n| HEADLINE | YES or NO | HIGH/MED/LOW Confidence |\n|----------|-----------|-------------------------|\n| Elon Musk April tweet markets overpricing low-count buckets | YES | MED[2][3] |\n| BTC >$114k Oct 15 undervalued for bull runs | NO | LOW[4] |\n| Tweet markets",
      "direction": "YES",
      "confidence": 0.6,
      "matched_markets": [
        "Will Trump name \"Elon\" or \"Musk\" in April?"
      ],
      "action": "WATCH",
      "x_link": null,
      "category": "COMMUNITY"
    }
  ],
  "stats": {
    "enter": 0,
    "alert": 15,
    "watch": 2,
    "high_conf": 0
  }
}