{
  "last_scan": "2026-04-23T00:10:34.609325+00:00",
  "scan_seconds": 39.0,
  "markets_scanned": 52,
  "open_positions": 13,
  "signals": [
    {
      "id": "sig_1776902998821_0",
      "timestamp": "2026-04-23T00:09:58.821778+00:00",
      "source": "PERPLEXITY",
      "headline": "Ethereum Price Surge Above $2,200 on U",
      "raw": "Ethereum Price Surge Above $2,200 on U.S.-Iran Ceasefire Announcement | YES | HIGH confidence** [3]\n\nEthereum's price rose +3.43% to $2,395.42 in the last 24 hours, explicitly linked to a U.S.-Iran ceasefire announcement boosting market sentiment[3]. Spot Ether ETFs recorded net inflows over $500 million this week, signaling strong institutional demand[3]. Prices climbed from $2,305 on April 21 to",
      "direction": "YES",
      "confidence": 0.78,
      "matched_markets": [
        "Ethereum Up or Down - April 23, 2:30AM-2:35AM ET"
      ],
      "action": "ALERT",
      "x_link": null,
      "category": "CRYPTO"
    },
    {
      "id": "sig_1776903003292_0",
      "timestamp": "2026-04-23T00:10:03.292873+00:00",
      "source": "PERPLEXITY",
      "headline": "Cooper Flagg Clinches NBA Rookie of the Year Favorite Status After Historic 51- and 45-Point Games** | YES | HIGH confid",
      "raw": "Cooper Flagg Clinches NBA Rookie of the Year Favorite Status After Historic 51- and 45-Point Games** | YES | HIGH confidence[1][2][3]\n\nDallas Mavericks rookie **Cooper Flagg** scored 51 points against the Orlando Magic on April 7, 2026, becoming the first teenager to reach 50 points in an NBA game, followed by 45 points in a 134-128 win over the **Los Angeles Lakers** on April 6, 2026\u2014marking back",
      "direction": "YES",
      "confidence": 0.65,
      "matched_markets": [
        "Will Cooper Flagg win the 2025\u201326 NBA Rookie of the Year award?",
        "Will Los Angeles Lakers advance to the Conference Semifinals in the 2026 NBA Pla",
        "Will Orlando Magic advance to the Conference Semifinals in the 2026 NBA Playoffs"
      ],
      "action": "ALERT",
      "x_link": null,
      "category": "SPORTS"
    },
    {
      "id": "sig_1776903009428_0",
      "timestamp": "2026-04-23T00:10:09.428554+00:00",
      "source": "PERPLEXITY",
      "headline": "I cannot provide the real-time information you're requesting based on these search results",
      "raw": "I cannot provide the real-time information you're requesting based on these search results. The results describe Polymarket's platform functionality and show some historical data from April 9-22, 2026, but they do not contain:",
      "direction": null,
      "confidence": 0.65,
      "matched_markets": [],
      "action": "ALERT",
      "x_link": null,
      "category": "COMMUNITY"
    },
    {
      "id": "sig_1776903009432_1",
      "timestamp": "2026-04-23T00:10:09.432017+00:00",
      "source": "PERPLEXITY",
      "headline": "Current X (Twitter) posts from Polymarket traders",
      "raw": "Current X (Twitter) posts from Polymarket traders",
      "direction": null,
      "confidence": 0.65,
      "matched_markets": [],
      "action": "ALERT",
      "x_link": null,
      "category": "COMMUNITY"
    },
    {
      "id": "sig_1776903009435_2",
      "timestamp": "2026-04-23T00:10:09.435543+00:00",
      "source": "PERPLEXITY",
      "headline": "Active whale bets or smart money moves happening right now",
      "raw": "Active whale bets or smart money moves happening right now",
      "direction": null,
      "confidence": 0.65,
      "matched_markets": [],
      "action": "ALERT",
      "x_link": null,
      "category": "COMMUNITY"
    },
    {
      "id": "sig_1776903009439_3",
      "timestamp": "2026-04-23T00:10:09.439038+00:00",
      "source": "PERPLEXITY",
      "headline": "Real-time discussion about mispriced markets",
      "raw": "Real-time discussion about mispriced markets",
      "direction": null,
      "confidence": 0.65,
      "matched_markets": [],
      "action": "ALERT",
      "x_link": null,
      "category": "COMMUNITY"
    },
    {
      "id": "sig_1776903009442_4",
      "timestamp": "2026-04-23T00:10:09.442556+00:00",
      "source": "PERPLEXITY",
      "headline": "Recent market-moving announcements or resolutions",
      "raw": "Recent market-moving announcements or resolutions\n\nTo get this information, you would need to:",
      "direction": null,
      "confidence": 0.65,
      "matched_markets": [],
      "action": "ALERT",
      "x_link": null,
      "category": "COMMUNITY"
    },
    {
      "id": "sig_1776903034591_0",
      "timestamp": "2026-04-23T00:10:34.591302+00:00",
      "source": "X_GROK",
      "headline": "US-Iran Diplomatic Meeting by April 23**: Heavy whale sell pressure crashed odds from 45% to 2% ($501k vol)",
      "raw": "US-Iran Diplomatic Meeting by April 23**: Heavy whale sell pressure crashed odds from 45% to 2% ($501k vol). Means NO. Confidence HIGH.[[1]](https://x.com/i/status/2047103918250004595)[[2]](https://x.com/i/status/2047103178231906808)",
      "direction": "NO",
      "confidence": 0.65,
      "matched_markets": [],
      "action": "ALERT",
      "x_link": "https://x.com/i/status/2047103918250004595)[[2]](https://x.com/i/status/2047103178231906808)",
      "category": "COMMUNITY"
    },
    {
      "id": "sig_1776903034595_1",
      "timestamp": "2026-04-23T00:10:34.595283+00:00",
      "source": "X_GROK",
      "headline": "US Invade Iran Before 2027**: 12 top traders (millions PNL) positioned NO ($16M vol)",
      "raw": "US Invade Iran Before 2027**: 12 top traders (millions PNL) positioned NO ($16M vol). Means NO. Confidence HIGH.[[3]](https://x.com/i/status/2047103811001700651)",
      "direction": "NO",
      "confidence": 0.65,
      "matched_markets": [],
      "action": "ALERT",
      "x_link": "https://x.com/i/status/2047103811001700651)",
      "category": "COMMUNITY"
    },
    {
      "id": "sig_1776903034598_2",
      "timestamp": "2026-04-23T00:10:34.598594+00:00",
      "source": "X_GROK",
      "headline": "Bitcoin Dip to $70k in April**: Whale bought $7",
      "raw": "Bitcoin Dip to $70k in April**: Whale bought $7.7k NO @91\u00a2. Means NO (stays above). Confidence MED.[[4]](https://x.com/i/status/2047103183030272373)",
      "direction": "NO",
      "confidence": 0.65,
      "matched_markets": [],
      "action": "ALERT",
      "x_link": "https://x.com/i/status/2047103183030272373)",
      "category": "COMMUNITY"
    },
    {
      "id": "sig_1776903034601_3",
      "timestamp": "2026-04-23T00:10:34.601810+00:00",
      "source": "X_GROK",
      "headline": "NBA Pistons ML vs Magic**: $747k+ whale conviction on Pistons @77\u00a2 (multiple alerts)",
      "raw": "NBA Pistons ML vs Magic**: $747k+ whale conviction on Pistons @77\u00a2 (multiple alerts). Means YES Pistons win. Confidence HIGH.[[5]](https://x.com/i/status/2047103421933666478)[[6]](https://x.com/i/status/2047094476821115285)",
      "direction": "YES",
      "confidence": 0.65,
      "matched_markets": [
        "NBA Playoffs: Who Will Win Series? - Pistons vs. Magic "
      ],
      "action": "ALERT",
      "x_link": "https://x.com/i/status/2047103421933666478)[[6]](https://x.com/i/status/2047094476821115285)",
      "category": "COMMUNITY"
    },
    {
      "id": "sig_1776903034604_4",
      "timestamp": "2026-04-23T00:10:34.604999+00:00",
      "source": "X_GROK",
      "headline": "NBA Thunder -16",
      "raw": "NBA Thunder -16.5 Spread vs Suns**: $200k++$103k whales on Thunder @51\u00a2. Means YES covers. Confidence MED.[[7]](https://x.com/i/status/2047097010533138630)[[8]](https://x.com/i/status/2047096258427310318)",
      "direction": "YES",
      "confidence": 0.65,
      "matched_markets": [],
      "action": "ALERT",
      "x_link": "https://x.com/i/status/2047097010533138630)[[8]](https://x.com/i/status/2047096258427310318)",
      "category": "COMMUNITY"
    },
    {
      "id": "sig_1776903034608_5",
      "timestamp": "2026-04-23T00:10:34.608521+00:00",
      "source": "X_GROK",
      "headline": "BlackRock BTC Buy $900M**: Bullish BTC signal, but only 10% odds for $150k in 2026",
      "raw": "BlackRock BTC Buy $900M**: Bullish BTC signal, but only 10% odds for $150k in 2026. Potential misprice if more buys. Means NO $150k soon. Confidence LOW.[[9]](https://x.com/i/status/2047085398933840127)[[10]](https://x.com/i/status/2047080243618255200)\n\nTrending: Sports whales dominate (NBA), geopolitics NO bets heavy amid tensions; platform bugs/whales discussed but no new mispricings flagged.[[1",
      "direction": "NO",
      "confidence": 0.65,
      "matched_markets": [],
      "action": "ALERT",
      "x_link": "https://x.com/i/status/2047085398933840127)[[10]](https://x.com/i/status/2047080243618255200)",
      "category": "COMMUNITY"
    }
  ],
  "stats": {
    "enter": 0,
    "alert": 13,
    "watch": 0,
    "high_conf": 0
  }
}