{
  "last_scan": "2026-04-16T19:53:37.550191+00:00",
  "scan_seconds": 26.4,
  "markets_scanned": 130,
  "open_positions": 87,
  "signals": [
    {
      "id": "sig_987118",
      "timestamp": "2026-04-16T19:53:30.748286+00:00",
      "source": "PERPLEXITY",
      "headline": "Ethereum:** Trading around $2,100 in early April[1]",
      "raw": "Ethereum:** Trading around $2,100 in early April[1].\n\nTo provide accurate \"breaking news\" for April 16, 2026, I would need search results from today or very recent sources that contain current market announcements, confirmed events, or resolved issues. The current results are outdated for your request. I recommend conducting a new search with today's date specifications to capture genuine breaking",
      "direction": null,
      "confidence": 0.9,
      "matched_markets": [
        "Will the price of Ethereum be above $2,000 on April 17?",
        "Will Ethereum dip to $1,600 April 13-19?"
      ],
      "action": "ALERT",
      "x_link": null,
      "category": "CRYPTO"
    },
    {
      "id": "sig_974495",
      "timestamp": "2026-04-16T19:53:18.125322+00:00",
      "source": "PERPLEXITY",
      "headline": "Trump Declares Iran War \"Basically Over\"** | YES | HIGH confidence[2]",
      "raw": "Trump Declares Iran War \"Basically Over\"** | YES | HIGH confidence[2]",
      "direction": "YES",
      "confidence": 0.65,
      "matched_markets": [],
      "action": "ALERT",
      "x_link": null,
      "category": "GEOPOLITICS"
    },
    {
      "id": "sig_974504",
      "timestamp": "2026-04-16T19:53:18.134691+00:00",
      "source": "PERPLEXITY",
      "headline": "Putin Delivers Emergency Speech Warning West Against Iran Intervention** | YES | MED confidence[1]",
      "raw": "Putin Delivers Emergency Speech Warning West Against Iran Intervention** | YES | MED confidence[1]",
      "direction": "YES",
      "confidence": 0.65,
      "matched_markets": [],
      "action": "ALERT",
      "x_link": null,
      "category": "GEOPOLITICS"
    },
    {
      "id": "sig_974514",
      "timestamp": "2026-04-16T19:53:18.144029+00:00",
      "source": "PERPLEXITY",
      "headline": "Trump Issues Ultimatum to Iran on Hormuz Blockade: \"Make a Deal or",
      "raw": "Trump Issues Ultimatum to Iran on Hormuz Blockade: \"Make a Deal or...\"** | YES | HIGH confidence[3]",
      "direction": "YES",
      "confidence": 0.65,
      "matched_markets": [],
      "action": "ALERT",
      "x_link": null,
      "category": "GEOPOLITICS"
    },
    {
      "id": "sig_987090",
      "timestamp": "2026-04-16T19:53:30.720700+00:00",
      "source": "PERPLEXITY",
      "headline": "I cannot provide the \"breaking news\" format you've requested based on these search results",
      "raw": "I cannot provide the \"breaking news\" format you've requested based on these search results. The articles provided are from early April 2026 (primarily April 1st), which are over two weeks old relative to the current date of April 16, 2026.\n\nThe search results contain the following relevant information from early April:",
      "direction": null,
      "confidence": 0.65,
      "matched_markets": [],
      "action": "ALERT",
      "x_link": null,
      "category": "CRYPTO"
    },
    {
      "id": "sig_987099",
      "timestamp": "2026-04-16T19:53:30.729956+00:00",
      "source": "PERPLEXITY",
      "headline": "Solana:** Trading around $82-83 with analysts projecting $88-$100 by end of April if a breakout confirms[3]",
      "raw": "Solana:** Trading around $82-83 with analysts projecting $88-$100 by end of April if a breakout confirms[3]. However, conflicting reports indicate SOL was down 13% over one week due to a $280M+ Drift protocol exploit involving social engineering, with support tested between $75-80[4].",
      "direction": "NO",
      "confidence": 0.65,
      "matched_markets": [
        "Will the price of Solana be above $100 on April 18?",
        "Solana Up or Down - April 17, 4:40AM-4:45AM ET"
      ],
      "action": "ALERT",
      "x_link": null,
      "category": "CRYPTO"
    },
    {
      "id": "sig_987109",
      "timestamp": "2026-04-16T19:53:30.739036+00:00",
      "source": "PERPLEXITY",
      "headline": "Bitcoin:** Analysts suggested potential movement toward $80,000, with stability above $68,000 viewed as a precursor[1]",
      "raw": "Bitcoin:** Analysts suggested potential movement toward $80,000, with stability above $68,000 viewed as a precursor[1].",
      "direction": null,
      "confidence": 0.65,
      "matched_markets": [],
      "action": "ALERT",
      "x_link": null,
      "category": "CRYPTO"
    },
    {
      "id": "sig_979469",
      "timestamp": "2026-04-16T19:53:23.099182+00:00",
      "source": "PERPLEXITY",
      "headline": "Trump Removes Truth Social Post Depicting Himself as Jesus; Vance Defends Trump Amid Backlash** | YES | MED confidence[1",
      "raw": "Trump Removes Truth Social Post Depicting Himself as Jesus; Vance Defends Trump Amid Backlash** | YES | MED confidence[1][2][3]\n\nJD Vance, as Vice President, addressed and defended President Trump's controversial Truth Social post portraying himself as Jesus\u2014now removed\u2014while criticizing Pope Leo XIV, during a Fox News appearance and a Turning Point USA rally in Georgia on April 14-15, 2026[1][2][",
      "direction": "YES",
      "confidence": 0.6,
      "matched_markets": [
        "Will the US x Iran ceasefire be extended by April 21, 2026?",
        "US x Iran permanent peace deal by April 30, 2026?",
        "US x Iran permanent peace deal by April 22, 2026?"
      ],
      "action": "WATCH",
      "x_link": null,
      "category": "POLITICS"
    },
    {
      "id": "sig_992919",
      "timestamp": "2026-04-16T19:53:36.549490+00:00",
      "source": "PERPLEXITY",
      "headline": "South Korea's annual inflation rose to 2",
      "raw": "South Korea's annual inflation rose to 2.2% in March 2026, up from 2.0% in prior months but below 2.4% forecasts | YES | HIGH confidence** [1]\n\nThis March figure, released around early April 2026 per source timing, marks a recent uptick driven by global energy volatility from Middle East conflict and weak won, keeping inflation above the Bank of Korea's 2% target.[1][4] The Bank of Korea confirmed",
      "direction": "YES",
      "confidence": 0.6,
      "matched_markets": [
        "Will South Korea\u2019s 2026 Annual Inflation be between 2.7% and 2.9%?"
      ],
      "action": "WATCH",
      "x_link": null,
      "category": "ECONOMICS"
    }
  ],
  "stats": {
    "enter": 0,
    "alert": 7,
    "watch": 2,
    "high_conf": 1
  }
}