{
  "last_scan": "2026-04-22T06:12:49.556295+00:00",
  "scan_seconds": 18.9,
  "markets_scanned": 83,
  "open_positions": 37,
  "signals": [
    {
      "id": "sig_1776838358144_0",
      "timestamp": "2026-04-22T06:12:38.144587+00:00",
      "source": "PERPLEXITY",
      "headline": "Kevin Warsh Criticizes Fed's Past Inflation Policy Errors Ahead of Powell Replacement Confirmation Hearing | NO | MED co",
      "raw": "Kevin Warsh Criticizes Fed's Past Inflation Policy Errors Ahead of Powell Replacement Confirmation Hearing | NO | MED confidence**  \nKevin Warsh, in his April 4, 2026 Senate confirmation hearing to replace Jerome Powell as Fed Chair, called the Fed's 2021-2022 policies a \"fatal policy error\" that let inflation soar, making it harder to control.[1]  \nFed Chair Powell stated on April 7, 2026, that t",
      "direction": "NO",
      "confidence": 0.9,
      "matched_markets": [
        "Will Powell say \"Tariff inflation\" during April press conference?"
      ],
      "action": "ENTER",
      "x_link": null,
      "category": "ECONOMICS"
    },
    {
      "id": "sig_1776838363431_0",
      "timestamp": "2026-04-22T06:12:43.431732+00:00",
      "source": "PERPLEXITY",
      "headline": "Lakers Crush Cavaliers 127-113 Behind Doncic's 42 Points, Clinch Top-6 West Playoff Spot & 50 Wins | NO (No Lakers-Cavs",
      "raw": "Lakers Crush Cavaliers 127-113 Behind Doncic's 42 Points, Clinch Top-6 West Playoff Spot & 50 Wins | NO (No Lakers-Cavs Series; Cavs Lead Raptors 2-0 in East Semis) | HIGH confidence**[1][2][3]\n\nLakers defeated Cavaliers on March 31, 2026 (not playoffs), with Luka Doncic's 42 points, 12 assists securing their 50th win (50-26), 4th straight victory, Pacific Division title, and guaranteed no worse t",
      "direction": "YES",
      "confidence": 0.9,
      "matched_markets": [
        "NBA Playoffs: Who Will Win Series? - Raptors vs. Cavaliers ",
        "Will Los Angeles Lakers advance to the Conference Semifinals in the 2026 NBA Pla",
        "Will Orlando Magic advance to the Conference Semifinals in the 2026 NBA Playoffs"
      ],
      "action": "ENTER",
      "x_link": null,
      "category": "SPORTS"
    },
    {
      "id": "sig_1776838368553_1",
      "timestamp": "2026-04-22T06:12:48.553310+00:00",
      "source": "PERPLEXITY",
      "headline": "GTA VI Release and Crypto Airdrops Draw News Story Bets | NO | MED confidence**",
      "raw": "GTA VI Release and Crypto Airdrops Draw News Story Bets | NO | MED confidence**\n\nIn News Stories markets (102 active, $56.2M volume), **GTA VI released before June 2026?** trades at 1% YES with $14M volume, signaling strong doubt, while **MegaETH airdrop by June 30, 2026?** sits at 57%[5]. Trending Markets (166 live, $3M+ volume) include niche bets like Nasdaq round-the-clock trading by June 30[1]",
      "direction": "YES",
      "confidence": 0.78,
      "matched_markets": [],
      "action": "ALERT",
      "x_link": null,
      "category": "COMMUNITY"
    },
    {
      "id": "sig_1776838353993_0",
      "timestamp": "2026-04-22T06:12:33.993159+00:00",
      "source": "PERPLEXITY",
      "headline": "Confidence: HIGH** (search results lack any real-time confirmations as of April 22, 2026)",
      "raw": "Confidence: HIGH** (search results lack any real-time confirmations as of April 22, 2026). [1][2][3][4][5][6]",
      "direction": null,
      "confidence": 0.65,
      "matched_markets": [],
      "action": "ALERT",
      "x_link": null,
      "category": "CRYPTO"
    },
    {
      "id": "sig_1776838368549_0",
      "timestamp": "2026-04-22T06:12:48.549546+00:00",
      "source": "PERPLEXITY",
      "headline": "Elon Musk Tweet Count Markets Lead Polymarket Activity | NO | LOW confidence**",
      "raw": "Elon Musk Tweet Count Markets Lead Polymarket Activity | NO | LOW confidence**\n\nPolymarket's most active markets as of April 21, 2026, center on **Elon Musk's tweet volume**, including \"Elon Musk # tweets April 17 - April 24, 2026?\" (with \"180-199\" at 29%) and \"Elon Musk musk # tweets in April 2026?\" (18% on 1080-1119), backed by over $17.1M in trading volume across 20+ Tweet Markets[2][3][4]. The",
      "direction": "NO",
      "confidence": 0.65,
      "matched_markets": [],
      "action": "ALERT",
      "x_link": null,
      "category": "COMMUNITY"
    }
  ],
  "stats": {
    "enter": 2,
    "alert": 3,
    "watch": 0,
    "high_conf": 2
  }
}