{
  "last_scan": "2026-04-23T07:21:00.091784+00:00",
  "scan_seconds": 19.5,
  "markets_scanned": 51,
  "open_positions": 13,
  "signals": [
    {
      "id": "sig_1776928844019_0",
      "timestamp": "2026-04-23T07:20:44.019228+00:00",
      "source": "PERPLEXITY",
      "headline": "Bitcoin Hits $78,194 on April 22, 2026 Amid Institutional ETF Surge and Regulatory Clarity | NO | HIGH confidence**",
      "raw": "Bitcoin Hits $78,194 on April 22, 2026 Amid Institutional ETF Surge and Regulatory Clarity | NO | HIGH confidence**\n\nBitcoin reached $78,194.37 at 9:15 a.m. ET on April 22, 2026, up $2,292 from the prior day, driven by record ETF inflows, corporate adoption (e.g., MicroStrategy's 300,000+ BTC), and supply constraints post-halving, breaching $75,000 resistance in mid-April for its strongest weekly ",
      "direction": "YES",
      "confidence": 0.9,
      "matched_markets": [
        "Bitcoin above 80,200 on April 23, 4AM ET?"
      ],
      "action": "ENTER",
      "x_link": null,
      "category": "CRYPTO"
    },
    {
      "id": "sig_1776928849955_1",
      "timestamp": "2026-04-23T07:20:49.955813+00:00",
      "source": "PERPLEXITY",
      "headline": "HEADLINE | Status | Confidence**",
      "raw": "HEADLINE | Status | Confidence**\n\nPowell Reaffirms He Will Remain Fed Chair Until Successor Confirmed | NO NEW DEVELOPMENTS | HIGH\n\nThe latest update shows Powell restating his commitment to serve as chair pro tempore if Kevin Warsh is not confirmed by his May 15 term end date[1][2][3]. Powell also confirmed he will not leave the Federal Reserve board until the ongoing Justice Department investiga",
      "direction": "NO",
      "confidence": 0.9,
      "matched_markets": [
        "Will Powell say \"Successor\" during April press conference?"
      ],
      "action": "ENTER",
      "x_link": null,
      "category": "ECONOMICS"
    },
    {
      "id": "sig_1776928849953_0",
      "timestamp": "2026-04-23T07:20:49.953708+00:00",
      "source": "PERPLEXITY",
      "headline": "Based on the search results provided, there is no breaking news from today (April 23, 2026) to report",
      "raw": "Based on the search results provided, there is no breaking news from today (April 23, 2026) to report. The most recent information available is from **April 21, 2026**, when Federal Reserve Chair Jerome Powell reiterated his position during a post-meeting news conference.",
      "direction": "NO",
      "confidence": 0.65,
      "matched_markets": [
        "Will Powell say \"Successor\" during April press conference?"
      ],
      "action": "ALERT",
      "x_link": null,
      "category": "ECONOMICS"
    },
    {
      "id": "sig_1776928849957_2",
      "timestamp": "2026-04-23T07:20:49.957728+00:00",
      "source": "PERPLEXITY",
      "headline": "Senate confirmation hearing for Kevin Warsh (not yet scheduled)[3]",
      "raw": "Senate confirmation hearing for Kevin Warsh (not yet scheduled)[3]",
      "direction": null,
      "confidence": 0.65,
      "matched_markets": [],
      "action": "ALERT",
      "x_link": null,
      "category": "ECONOMICS"
    },
    {
      "id": "sig_1776928849959_3",
      "timestamp": "2026-04-23T07:20:49.959595+00:00",
      "source": "PERPLEXITY",
      "headline": "Resolution of the DOJ investigation into Fed renovations[3]",
      "raw": "Resolution of the DOJ investigation into Fed renovations[3]",
      "direction": null,
      "confidence": 0.65,
      "matched_markets": [],
      "action": "ALERT",
      "x_link": null,
      "category": "ECONOMICS"
    },
    {
      "id": "sig_1776928849961_4",
      "timestamp": "2026-04-23T07:20:49.961508+00:00",
      "source": "PERPLEXITY",
      "headline": "Trump administration's plans to challenge a federal judge's ruling that quashed grand jury subpoenas in the investigatio",
      "raw": "Trump administration's plans to challenge a federal judge's ruling that quashed grand jury subpoenas in the investigation[3]",
      "direction": null,
      "confidence": 0.65,
      "matched_markets": [],
      "action": "ALERT",
      "x_link": null,
      "category": "ECONOMICS"
    },
    {
      "id": "sig_1776928859088_0",
      "timestamp": "2026-04-23T07:20:59.088106+00:00",
      "source": "PERPLEXITY",
      "headline": "SCOTUS Sports Event Contract Case Acceptance by Dec 31 at 37% | NO major whale bets or tips spotted | LOW confidence**",
      "raw": "SCOTUS Sports Event Contract Case Acceptance by Dec 31 at 37% | NO major whale bets or tips spotted | LOW confidence**  \nPolymarket's trending markets show the most active as \u201cSCOTUS accepts sports event contract case by Dec 31?\u201d with crowd odds at 37% yes, amid $3.3M volume across 168 trending markets including 2026 inflation highs and Nasdaq 24/7 trading by June 30[1]. No recent X posts from tra",
      "direction": "YES",
      "confidence": 0.65,
      "matched_markets": [
        "Bitcoin above 80,200 on April 23, 4AM ET?"
      ],
      "action": "ALERT",
      "x_link": null,
      "category": "COMMUNITY"
    }
  ],
  "stats": {
    "enter": 2,
    "alert": 5,
    "watch": 0,
    "high_conf": 2
  }
}